LICENSE.txt
MANIFEST.in
README.md
setup.py
tmkpy.cpp
tmkpy.h
tmkpy.i
tmkpy.py
pdq/LICENSE
pdq/cpp/CImg.h
pdq/cpp/Makefile
pdq/cpp/README.md
pdq/cpp/bin/README.md
pdq/cpp/bin/clusterize256.cpp
pdq/cpp/bin/clusterize256x.cpp
pdq/cpp/bin/hamming-tabulate.cpp
pdq/cpp/bin/hashtool256.cpp
pdq/cpp/bin/htmlify-clusters-plain.rb
pdq/cpp/bin/htmlify-clusters.rb
pdq/cpp/bin/htmlify-pairs.rb
pdq/cpp/bin/htmlify-photos-distance.rb
pdq/cpp/bin/htmlify-photos-plain.rb
pdq/cpp/bin/htmlify-photos-quality.rb
pdq/cpp/bin/htmlify-photos.rb
pdq/cpp/bin/mih-query.cpp
pdq/cpp/bin/pdq-downsample-demo.cpp
pdq/cpp/bin/pdq-photo-hasher.cpp
pdq/cpp/bin/snowball-clusterize256.cpp
pdq/cpp/bin/test-bits.cpp
pdq/cpp/bin/test-hamming.cpp
pdq/cpp/bin/test-mih.cpp
pdq/cpp/common/pdqbasetypes.h
pdq/cpp/common/pdqhamming.cpp
pdq/cpp/common/pdqhamming.h
pdq/cpp/common/pdqhashtypes.cpp
pdq/cpp/common/pdqhashtypes.h
pdq/cpp/downscaling/downscaling.cpp
pdq/cpp/downscaling/downscaling.h
pdq/cpp/downscaling/downscaling.o
pdq/cpp/hashing/pdqhashing.cpp
pdq/cpp/hashing/pdqhashing.h
pdq/cpp/hashing/pdqhashing.o
pdq/cpp/hashing/torben.cpp
pdq/cpp/hashing/torben.h
pdq/cpp/hashing/torben.o
pdq/cpp/index/mih.h
pdq/cpp/io/hashio.cpp
pdq/cpp/io/hashio.h
pdq/cpp/io/pdqio.cpp
pdq/cpp/io/pdqio.h
pdq/cpp/output-regtest/out
pdq/cpp/reg_test/run
pdq/cpp/reg_test/expected/out
tmk/LICENSE
tmk/cpp/Makefile
tmk/cpp/Makefile~
tmk/cpp/README.md
tmk/cpp/libtmk.a
tmk/cpp/algo/tmkfv.cpp
tmk/cpp/algo/tmkfv.h
tmk/cpp/algo/tmkfv.o
tmk/cpp/bin/feat2tmk.cpp
tmk/cpp/bin/featdump.cpp
tmk/cpp/bin/time-resampler-demo.cpp
tmk/cpp/bin/tmk-clusterize.cpp
tmk/cpp/bin/tmk-compare-two-tmks.cpp
tmk/cpp/bin/tmk-compute-dataset-mean-feature.cpp
tmk/cpp/bin/tmk-find-cluster-reps.cpp
tmk/cpp/bin/tmk-hash-video.cpp
tmk/cpp/bin/tmk-query-with-faiss.cpp
tmk/cpp/bin/tmk-query.cpp
tmk/cpp/bin/tmk-show-pair-offsets.cpp
tmk/cpp/bin/tmk-two-level-score.cpp
tmk/cpp/bin/tmk_default_thresholds.h
tmk/cpp/bin/tmkdump.cpp
tmk/cpp/bin/vid2vstr.cpp
tmkpy.egg-info/PKG-INFO
tmkpy.egg-info/SOURCES.txt
tmkpy.egg-info/dependency_links.txt
tmkpy.egg-info/top_level.txt