Metadata-Version: 2.1
Name: tmkpy
Version: 0.1.1
Summary: Python bindings for the TMK video similarity library
Home-page: https://github.com/meedan/tmkpy
Author: Scott Hale
Author-email: scott@meedan.com
License: UNKNOWN
Platform: UNKNOWN
